{"434372": {"geometry": {"type": "Point", "coordinates": [-122.334155, 47.611018333333334]}, "type": "Feature", "properties": {"time": 1563742771, "jump_ebike_battery_level": "74%", "bike_id": "bike_177067", "name": "07819"}}, "434371": {"geometry": {"type": "Point", "coordinates": [-122.333615, 47.611445]}, "type": "Feature", "properties": {"time": 1563739174, "jump_ebike_battery_level": "74%", "bike_id": "bike_177067", "name": "07819"}}, "434370": {"geometry": {"type": "Point", "coordinates": [-122.33789666666667, 47.60957333333333]}, "type": "Feature", "properties": {"time": 1563735574, "jump_ebike_battery_level": "74%", "bike_id": "bike_177067", "name": "07819"}}, "434377": {"geometry": {"type": "Point", "coordinates": [-122.34171166666667, 47.611625]}, "type": "Feature", "properties": {"time": 1563757213, "jump_ebike_battery_level": "72%", "bike_id": "bike_177067", "name": "07819"}}, "434376": {"geometry": {"type": "Point", "coordinates": [-122.34097, 47.60977]}, "type": "Feature", "properties": {"time": 1563753613, "jump_ebike_battery_level": "72%", "bike_id": "bike_177067", "name": "07819"}}, "434374": {"geometry": {"type": "Point", "coordinates": [-122.34097, 47.60977]}, "type": "Feature", "properties": {"time": 1563749972, "jump_ebike_battery_level": "73%", "bike_id": "bike_177067", "name": "07819"}}, "434395": {"geometry": {"type": "Point", "coordinates": [-122.33988333333333, 47.621761666666664]}, "type": "Feature", "properties": {"time": 1563822218, "jump_ebike_battery_level": "66%", "bike_id": "bike_177067", "name": "07819"}}, "434394": {"geometry": {"type": "Point", "coordinates": [-122.339485, 47.6222]}, "type": "Feature", "properties": {"time": 1563818616, "jump_ebike_battery_level": "67%", "bike_id": "bike_177067", "name": "07819"}}, "434397": {"geometry": {"type": "Point", "coordinates": [-122.34243333333333, 47.61682833333333]}, "type": "Feature", "properties": {"time": 1563829417, "jump_ebike_battery_level": "66%", "bike_id": "bike_177067", "name": "07819"}}, "434396": {"geometry": {"type": "Point", "coordinates": [-122.33988333333333, 47.621761666666664]}, "type": "Feature", "properties": {"time": 1563825829, "jump_ebike_battery_level": "66%", "bike_id": "bike_177067", "name": "07819"}}, "434391": {"geometry": {"type": "Point", "coordinates": [-122.36072333333334, 47.621916666666664]}, "type": "Feature", "properties": {"time": 1563807830, "jump_ebike_battery_level": "67%", "bike_id": "bike_177067", "name": "07819"}}, "434390": {"geometry": {"type": "Point", "coordinates": [-122.36072333333334, 47.621916666666664]}, "type": "Feature", "properties": {"time": 1563804217, "jump_ebike_battery_level": "68%", "bike_id": "bike_177067", "name": "07819"}}, "434393": {"geometry": {"type": "Point", "coordinates": [-122.339485, 47.6222]}, "type": "Feature", "properties": {"time": 1563815015, "jump_ebike_battery_level": "66%", "bike_id": "bike_177067", "name": "07819"}}, "434392": {"geometry": {"type": "Point", "coordinates": [-122.339485, 47.6222]}, "type": "Feature", "properties": {"time": 1563811413, "jump_ebike_battery_level": "66%", "bike_id": "bike_177067", "name": "07819"}}, "434369": {"geometry": {"type": "Point", "coordinates": [-122.33789666666667, 47.60957333333333]}, "type": "Feature", "properties": {"time": 1563731974, "jump_ebike_battery_level": "75%", "bike_id": "bike_177067", "name": "07819"}}, "434364": {"geometry": {"type": "Point", "coordinates": [-122.37258166666666, 47.626255]}, "type": "Feature", "properties": {"time": 1563710413, "jump_ebike_battery_level": "78%", "bike_id": "bike_177067", "name": "07819"}}, "434365": {"geometry": {"type": "Point", "coordinates": [-122.37258166666666, 47.626255]}, "type": "Feature", "properties": {"time": 1563714014, "jump_ebike_battery_level": "78%", "bike_id": "bike_177067", "name": "07819"}}, "434366": {"geometry": {"type": "Point", "coordinates": [-122.37258166666666, 47.626255]}, "type": "Feature", "properties": {"time": 1563717614, "jump_ebike_battery_level": "78%", "bike_id": "bike_177067", "name": "07819"}}, "434367": {"geometry": {"type": "Point", "coordinates": [-122.37258166666666, 47.626255]}, "type": "Feature", "properties": {"time": 1563721213, "jump_ebike_battery_level": "78%", "bike_id": "bike_177067", "name": "07819"}}, "434361": {"geometry": {"type": "Point", "coordinates": [-122.37258166666666, 47.626255]}, "type": "Feature", "properties": {"time": 1563699613, "jump_ebike_battery_level": "80%", "bike_id": "bike_177067", "name": "07819"}}, "434362": {"geometry": {"type": "Point", "coordinates": [-122.37258166666666, 47.626255]}, "type": "Feature", "properties": {"time": 1563706777, "jump_ebike_battery_level": "80%", "bike_id": "bike_177067", "name": "07819"}}, "434386": {"geometry": {"type": "Point", "coordinates": [-122.36072333333334, 47.621916666666664]}, "type": "Feature", "properties": {"time": 1563789830, "jump_ebike_battery_level": "69%", "bike_id": "bike_177067", "name": "07819"}}, "434387": {"geometry": {"type": "Point", "coordinates": [-122.36072333333334, 47.621916666666664]}, "type": "Feature", "properties": {"time": 1563793414, "jump_ebike_battery_level": "69%", "bike_id": "bike_177067", "name": "07819"}}, "434384": {"geometry": {"type": "Point", "coordinates": [-122.36072333333334, 47.621916666666664]}, "type": "Feature", "properties": {"time": 1563782614, "jump_ebike_battery_level": "69%", "bike_id": "bike_177067", "name": "07819"}}, "434385": {"geometry": {"type": "Point", "coordinates": [-122.36072333333334, 47.621916666666664]}, "type": "Feature", "properties": {"time": 1563786232, "jump_ebike_battery_level": "69%", "bike_id": "bike_177067", "name": "07819"}}, "434382": {"geometry": {"type": "Point", "coordinates": [-122.36072333333334, 47.621916666666664]}, "type": "Feature", "properties": {"time": 1563775213, "jump_ebike_battery_level": "70%", "bike_id": "bike_177067", "name": "07819"}}, "434383": {"geometry": {"type": "Point", "coordinates": [-122.36072333333334, 47.621916666666664]}, "type": "Feature", "properties": {"time": 1563782376, "jump_ebike_battery_level": "69%", "bike_id": "bike_177067", "name": "07819"}}, "434381": {"geometry": {"type": "Point", "coordinates": [-122.36072333333334, 47.621916666666664]}, "type": "Feature", "properties": {"time": 1563771613, "jump_ebike_battery_level": "70%", "bike_id": "bike_177067", "name": "07819"}}, "434388": {"geometry": {"type": "Point", "coordinates": [-122.36072333333334, 47.621916666666664]}, "type": "Feature", "properties": {"time": 1563797013, "jump_ebike_battery_level": "69%", "bike_id": "bike_177067", "name": "07819"}}, "434389": {"geometry": {"type": "Point", "coordinates": [-122.36072333333334, 47.621916666666664]}, "type": "Feature", "properties": {"time": 1563800613, "jump_ebike_battery_level": "69%", "bike_id": "bike_177067", "name": "07819"}}}