{"434536": {"geometry": {"type": "Point", "coordinates": [-122.32084166666667, 47.616015]}, "type": "Feature", "properties": {"time": 1564329816, "jump_ebike_battery_level": "85%", "bike_id": "bike_79098", "name": "09737"}}, "434539": {"geometry": {"type": "Point", "coordinates": [-122.32084166666667, 47.616015]}, "type": "Feature", "properties": {"time": 1564340615, "jump_ebike_battery_level": "84%", "bike_id": "bike_79098", "name": "09737"}}, "434538": {"geometry": {"type": "Point", "coordinates": [-122.32084166666667, 47.616015]}, "type": "Feature", "properties": {"time": 1564337029, "jump_ebike_battery_level": "85%", "bike_id": "bike_79098", "name": "09737"}}, "434528": {"geometry": {"type": "Point", "coordinates": [-122.32780333333334, 47.61548]}, "type": "Feature", "properties": {"time": 1564301029, "jump_ebike_battery_level": "86%", "bike_id": "bike_79098", "name": "09737"}}, "434529": {"geometry": {"type": "Point", "coordinates": [-122.32780333333334, 47.61548]}, "type": "Feature", "properties": {"time": 1564304630, "jump_ebike_battery_level": "86%", "bike_id": "bike_79098", "name": "09737"}}, "434526": {"geometry": {"type": "Point", "coordinates": [-122.33236, 47.62224]}, "type": "Feature", "properties": {"time": 1564293829, "jump_ebike_battery_level": "91%", "bike_id": "bike_79098", "name": "09737"}}, "434527": {"geometry": {"type": "Point", "coordinates": [-122.32780333333334, 47.61548]}, "type": "Feature", "properties": {"time": 1564297429, "jump_ebike_battery_level": "86%", "bike_id": "bike_79098", "name": "09737"}}, "434524": {"geometry": {"type": "Point", "coordinates": [-122.33236, 47.62224]}, "type": "Feature", "properties": {"time": 1564286629, "jump_ebike_battery_level": "92%", "bike_id": "bike_79098", "name": "09737"}}, "434525": {"geometry": {"type": "Point", "coordinates": [-122.33236, 47.62224]}, "type": "Feature", "properties": {"time": 1564290215, "jump_ebike_battery_level": "91%", "bike_id": "bike_79098", "name": "09737"}}, "434531": {"geometry": {"type": "Point", "coordinates": [-122.32780333333334, 47.61548]}, "type": "Feature", "properties": {"time": 1564311829, "jump_ebike_battery_level": "86%", "bike_id": "bike_79098", "name": "09737"}}, "434523": {"geometry": {"type": "Point", "coordinates": [-122.33236, 47.62224]}, "type": "Feature", "properties": {"time": 1564283019, "jump_ebike_battery_level": "92%", "bike_id": "bike_79098", "name": "09737"}}, "434533": {"geometry": {"type": "Point", "coordinates": [-122.32780333333334, 47.61548]}, "type": "Feature", "properties": {"time": 1564319029, "jump_ebike_battery_level": "86%", "bike_id": "bike_79098", "name": "09737"}}, "434530": {"geometry": {"type": "Point", "coordinates": [-122.32780333333334, 47.61548]}, "type": "Feature", "properties": {"time": 1564308229, "jump_ebike_battery_level": "86%", "bike_id": "bike_79098", "name": "09737"}}, "434553": {"geometry": {"type": "Point", "coordinates": [-122.30391666666667, 47.663511666666665]}, "type": "Feature", "properties": {"time": 1564391020, "jump_ebike_battery_level": "63%", "bike_id": "bike_79098", "name": "09737"}}, "434552": {"geometry": {"type": "Point", "coordinates": [-122.30391666666667, 47.663511666666665]}, "type": "Feature", "properties": {"time": 1564387430, "jump_ebike_battery_level": "64%", "bike_id": "bike_79098", "name": "09737"}}, "434532": {"geometry": {"type": "Point", "coordinates": [-122.32780333333334, 47.61548]}, "type": "Feature", "properties": {"time": 1564315429, "jump_ebike_battery_level": "86%", "bike_id": "bike_79098", "name": "09737"}}, "434551": {"geometry": {"type": "Point", "coordinates": [-122.30391666666667, 47.663511666666665]}, "type": "Feature", "properties": {"time": 1564383830, "jump_ebike_battery_level": "64%", "bike_id": "bike_79098", "name": "09737"}}, "434556": {"geometry": {"type": "Point", "coordinates": [-122.30391666666667, 47.663511666666665]}, "type": "Feature", "properties": {"time": 1564401829, "jump_ebike_battery_level": "63%", "bike_id": "bike_79098", "name": "09737"}}, "434550": {"geometry": {"type": "Point", "coordinates": [-122.30391666666667, 47.663511666666665]}, "type": "Feature", "properties": {"time": 1564380230, "jump_ebike_battery_level": "64%", "bike_id": "bike_79098", "name": "09737"}}, "434554": {"geometry": {"type": "Point", "coordinates": [-122.30391666666667, 47.663511666666665]}, "type": "Feature", "properties": {"time": 1564394629, "jump_ebike_battery_level": "63%", "bike_id": "bike_79098", "name": "09737"}}, "434541": {"geometry": {"type": "Point", "coordinates": [-122.31843666666667, 47.63041]}, "type": "Feature", "properties": {"time": 1564347830, "jump_ebike_battery_level": "78%", "bike_id": "bike_79098", "name": "09737"}}, "434535": {"geometry": {"type": "Point", "coordinates": [-122.32780333333334, 47.61548]}, "type": "Feature", "properties": {"time": 1564326187, "jump_ebike_battery_level": "86%", "bike_id": "bike_79098", "name": "09737"}}, "434559": {"geometry": {"type": "Point", "coordinates": [-122.30391666666667, 47.663511666666665]}, "type": "Feature", "properties": {"time": 1564412614, "jump_ebike_battery_level": "63%", "bike_id": "bike_79098", "name": "09737"}}, "434558": {"geometry": {"type": "Point", "coordinates": [-122.30391666666667, 47.663511666666665]}, "type": "Feature", "properties": {"time": 1564409030, "jump_ebike_battery_level": "63%", "bike_id": "bike_79098", "name": "09737"}}, "434548": {"geometry": {"type": "Point", "coordinates": [-122.30391666666667, 47.663511666666665]}, "type": "Feature", "properties": {"time": 1564373017, "jump_ebike_battery_level": "63%", "bike_id": "bike_79098", "name": "09737"}}, "434549": {"geometry": {"type": "Point", "coordinates": [-122.30391666666667, 47.663511666666665]}, "type": "Feature", "properties": {"time": 1564376612, "jump_ebike_battery_level": "64%", "bike_id": "bike_79098", "name": "09737"}}, "434534": {"geometry": {"type": "Point", "coordinates": [-122.32780333333334, 47.61548]}, "type": "Feature", "properties": {"time": 1564322615, "jump_ebike_battery_level": "86%", "bike_id": "bike_79098", "name": "09737"}}, "434544": {"geometry": {"type": "Point", "coordinates": [-122.29761333333333, 47.66344333333333]}, "type": "Feature", "properties": {"time": 1564358629, "jump_ebike_battery_level": "69%", "bike_id": "bike_79098", "name": "09737"}}, "434545": {"geometry": {"type": "Point", "coordinates": [-122.29761333333333, 47.66344333333333]}, "type": "Feature", "properties": {"time": 1564362216, "jump_ebike_battery_level": "68%", "bike_id": "bike_79098", "name": "09737"}}, "434546": {"geometry": {"type": "Point", "coordinates": [-122.30391666666667, 47.663511666666665]}, "type": "Feature", "properties": {"time": 1564365815, "jump_ebike_battery_level": "64%", "bike_id": "bike_79098", "name": "09737"}}, "434547": {"geometry": {"type": "Point", "coordinates": [-122.30391666666667, 47.663511666666665]}, "type": "Feature", "properties": {"time": 1564369414, "jump_ebike_battery_level": "63%", "bike_id": "bike_79098", "name": "09737"}}, "434557": {"geometry": {"type": "Point", "coordinates": [-122.30391666666667, 47.663511666666665]}, "type": "Feature", "properties": {"time": 1564405430, "jump_ebike_battery_level": "63%", "bike_id": "bike_79098", "name": "09737"}}, "434537": {"geometry": {"type": "Point", "coordinates": [-122.32084166666667, 47.616015]}, "type": "Feature", "properties": {"time": 1564333415, "jump_ebike_battery_level": "85%", "bike_id": "bike_79098", "name": "09737"}}, "434555": {"geometry": {"type": "Point", "coordinates": [-122.30391666666667, 47.663511666666665]}, "type": "Feature", "properties": {"time": 1564398218, "jump_ebike_battery_level": "63%", "bike_id": "bike_79098", "name": "09737"}}, "434543": {"geometry": {"type": "Point", "coordinates": [-122.29761333333333, 47.66344333333333]}, "type": "Feature", "properties": {"time": 1564355014, "jump_ebike_battery_level": "69%", "bike_id": "bike_79098", "name": "09737"}}}