{"434489": {"geometry": {"type": "Point", "coordinates": [-122.33469833333334, 47.61286833333333]}, "type": "Feature", "properties": {"time": 1564160617, "jump_ebike_battery_level": "80%", "bike_id": "bike_86081", "name": "09797"}}, "434488": {"geometry": {"type": "Point", "coordinates": [-122.32073166666666, 47.619595]}, "type": "Feature", "properties": {"time": 1564157029, "jump_ebike_battery_level": "81%", "bike_id": "bike_86081", "name": "09797"}}, "434490": {"geometry": {"type": "Point", "coordinates": [-122.33469833333334, 47.61286833333333]}, "type": "Feature", "properties": {"time": 1564164217, "jump_ebike_battery_level": "80%", "bike_id": "bike_86081", "name": "09797"}}, "434487": {"geometry": {"type": "Point", "coordinates": [-122.32073166666666, 47.619595]}, "type": "Feature", "properties": {"time": 1564153429, "jump_ebike_battery_level": "83%", "bike_id": "bike_86081", "name": "09797"}}}