{"434379": {"geometry": {"type": "Point", "coordinates": [-122.37736666666666, 47.586664999999996]}, "type": "Feature", "properties": {"time": 1563767975, "jump_ebike_battery_level": "50%", "bike_id": "bike_209806", "name": "15516"}}, "434378": {"geometry": {"type": "Point", "coordinates": [-122.37736666666666, 47.586664999999996]}, "type": "Feature", "properties": {"time": 1563764375, "jump_ebike_battery_level": "49%", "bike_id": "bike_209806", "name": "15516"}}, "434372": {"geometry": {"type": "Point", "coordinates": [-122.38387166666666, 47.59453666666667]}, "type": "Feature", "properties": {"time": 1563742771, "jump_ebike_battery_level": "70%", "bike_id": "bike_209806", "name": "15516"}}, "434371": {"geometry": {"type": "Point", "coordinates": [-122.40494166666667, 47.581495]}, "type": "Feature", "properties": {"time": 1563739174, "jump_ebike_battery_level": "72%", "bike_id": "bike_209806", "name": "15516"}}, "434370": {"geometry": {"type": "Point", "coordinates": [-122.40494166666667, 47.581495]}, "type": "Feature", "properties": {"time": 1563735574, "jump_ebike_battery_level": "72%", "bike_id": "bike_209806", "name": "15516"}}, "434377": {"geometry": {"type": "Point", "coordinates": [-122.38156166666667, 47.589708333333334]}, "type": "Feature", "properties": {"time": 1563757213, "jump_ebike_battery_level": "60%", "bike_id": "bike_209806", "name": "15516"}}, "434376": {"geometry": {"type": "Point", "coordinates": [-122.40954833333333, 47.579541666666664]}, "type": "Feature", "properties": {"time": 1563753613, "jump_ebike_battery_level": "66%", "bike_id": "bike_209806", "name": "15516"}}, "434374": {"geometry": {"type": "Point", "coordinates": [-122.40259666666667, 47.58255]}, "type": "Feature", "properties": {"time": 1563749972, "jump_ebike_battery_level": "66%", "bike_id": "bike_209806", "name": "15516"}}, "434498": {"geometry": {"type": "Point", "coordinates": [-122.40056833333334, 47.530355]}, "type": "Feature", "properties": {"time": 1564193029, "jump_ebike_battery_level": "23%", "bike_id": "bike_209806", "name": "15516"}}, "434492": {"geometry": {"type": "Point", "coordinates": [-122.39311666666667, 47.53109333333333]}, "type": "Feature", "properties": {"time": 1564171429, "jump_ebike_battery_level": "32%", "bike_id": "bike_209806", "name": "15516"}}, "434493": {"geometry": {"type": "Point", "coordinates": [-122.38703833333334, 47.54335666666667]}, "type": "Feature", "properties": {"time": 1564175030, "jump_ebike_battery_level": "28%", "bike_id": "bike_209806", "name": "15516"}}, "434490": {"geometry": {"type": "Point", "coordinates": [-122.39311666666667, 47.53109333333333]}, "type": "Feature", "properties": {"time": 1564164217, "jump_ebike_battery_level": "33%", "bike_id": "bike_209806", "name": "15516"}}, "434491": {"geometry": {"type": "Point", "coordinates": [-122.39311666666667, 47.53109333333333]}, "type": "Feature", "properties": {"time": 1564167817, "jump_ebike_battery_level": "33%", "bike_id": "bike_209806", "name": "15516"}}, "434496": {"geometry": {"type": "Point", "coordinates": [-122.39324, 47.52999666666667]}, "type": "Feature", "properties": {"time": 1564185815, "jump_ebike_battery_level": "25%", "bike_id": "bike_209806", "name": "15516"}}, "434497": {"geometry": {"type": "Point", "coordinates": [-122.40056833333334, 47.530355]}, "type": "Feature", "properties": {"time": 1564189416, "jump_ebike_battery_level": "24%", "bike_id": "bike_209806", "name": "15516"}}, "434494": {"geometry": {"type": "Point", "coordinates": [-122.39324, 47.52999666666667]}, "type": "Feature", "properties": {"time": 1564178612, "jump_ebike_battery_level": "21%", "bike_id": "bike_209806", "name": "15516"}}, "434495": {"geometry": {"type": "Point", "coordinates": [-122.39324, 47.52999666666667]}, "type": "Feature", "properties": {"time": 1564182212, "jump_ebike_battery_level": "26%", "bike_id": "bike_209806", "name": "15516"}}, "434386": {"geometry": {"type": "Point", "coordinates": [-122.37736666666666, 47.586664999999996]}, "type": "Feature", "properties": {"time": 1563789830, "jump_ebike_battery_level": "48%", "bike_id": "bike_209806", "name": "15516"}}, "434387": {"geometry": {"type": "Point", "coordinates": [-122.37736666666666, 47.586664999999996]}, "type": "Feature", "properties": {"time": 1563793414, "jump_ebike_battery_level": "48%", "bike_id": "bike_209806", "name": "15516"}}, "434384": {"geometry": {"type": "Point", "coordinates": [-122.37736666666666, 47.586664999999996]}, "type": "Feature", "properties": {"time": 1563782614, "jump_ebike_battery_level": "48%", "bike_id": "bike_209806", "name": "15516"}}, "434385": {"geometry": {"type": "Point", "coordinates": [-122.37736666666666, 47.586664999999996]}, "type": "Feature", "properties": {"time": 1563786232, "jump_ebike_battery_level": "48%", "bike_id": "bike_209806", "name": "15516"}}, "434382": {"geometry": {"type": "Point", "coordinates": [-122.37736666666666, 47.586664999999996]}, "type": "Feature", "properties": {"time": 1563775213, "jump_ebike_battery_level": "49%", "bike_id": "bike_209806", "name": "15516"}}, "434383": {"geometry": {"type": "Point", "coordinates": [-122.37736666666666, 47.586664999999996]}, "type": "Feature", "properties": {"time": 1563782376, "jump_ebike_battery_level": "48%", "bike_id": "bike_209806", "name": "15516"}}, "434381": {"geometry": {"type": "Point", "coordinates": [-122.37736666666666, 47.586664999999996]}, "type": "Feature", "properties": {"time": 1563771613, "jump_ebike_battery_level": "50%", "bike_id": "bike_209806", "name": "15516"}}, "434388": {"geometry": {"type": "Point", "coordinates": [-122.37736666666666, 47.586664999999996]}, "type": "Feature", "properties": {"time": 1563797013, "jump_ebike_battery_level": "48%", "bike_id": "bike_209806", "name": "15516"}}, "434389": {"geometry": {"type": "Point", "coordinates": [-122.37736666666666, 47.586664999999996]}, "type": "Feature", "properties": {"time": 1563800613, "jump_ebike_battery_level": "48%", "bike_id": "bike_209806", "name": "15516"}}, "434467": {"geometry": {"type": "Point", "coordinates": [-122.393165, 47.52317166666667]}, "type": "Feature", "properties": {"time": 1564081430, "jump_ebike_battery_level": "52%", "bike_id": "bike_209806", "name": "15516"}}, "434466": {"geometry": {"type": "Point", "coordinates": [-122.393165, 47.52317166666667]}, "type": "Feature", "properties": {"time": 1564077815, "jump_ebike_battery_level": "52%", "bike_id": "bike_209806", "name": "15516"}}, "434465": {"geometry": {"type": "Point", "coordinates": [-122.393165, 47.52317166666667]}, "type": "Feature", "properties": {"time": 1564074216, "jump_ebike_battery_level": "53%", "bike_id": "bike_209806", "name": "15516"}}, "434464": {"geometry": {"type": "Point", "coordinates": [-122.393165, 47.52317166666667]}, "type": "Feature", "properties": {"time": 1564070629, "jump_ebike_battery_level": "54%", "bike_id": "bike_209806", "name": "15516"}}, "434463": {"geometry": {"type": "Point", "coordinates": [-122.393165, 47.52317166666667]}, "type": "Feature", "properties": {"time": 1564067030, "jump_ebike_battery_level": "54%", "bike_id": "bike_209806", "name": "15516"}}, "434462": {"geometry": {"type": "Point", "coordinates": [-122.393165, 47.52317166666667]}, "type": "Feature", "properties": {"time": 1564063418, "jump_ebike_battery_level": "55%", "bike_id": "bike_209806", "name": "15516"}}, "434461": {"geometry": {"type": "Point", "coordinates": [-122.393165, 47.52317166666667]}, "type": "Feature", "properties": {"time": 1564059830, "jump_ebike_battery_level": "55%", "bike_id": "bike_209806", "name": "15516"}}, "434460": {"geometry": {"type": "Point", "coordinates": [-122.393165, 47.52317166666667]}, "type": "Feature", "properties": {"time": 1564056230, "jump_ebike_battery_level": "56%", "bike_id": "bike_209806", "name": "15516"}}, "434469": {"geometry": {"type": "Point", "coordinates": [-122.393165, 47.52317166666667]}, "type": "Feature", "properties": {"time": 1564088629, "jump_ebike_battery_level": "52%", "bike_id": "bike_209806", "name": "15516"}}, "434468": {"geometry": {"type": "Point", "coordinates": [-122.393165, 47.52317166666667]}, "type": "Feature", "properties": {"time": 1564085016, "jump_ebike_battery_level": "52%", "bike_id": "bike_209806", "name": "15516"}}, "434489": {"geometry": {"type": "Point", "coordinates": [-122.39311666666667, 47.53109333333333]}, "type": "Feature", "properties": {"time": 1564160617, "jump_ebike_battery_level": "32%", "bike_id": "bike_209806", "name": "15516"}}, "434488": {"geometry": {"type": "Point", "coordinates": [-122.39311666666667, 47.53109333333333]}, "type": "Feature", "properties": {"time": 1564157029, "jump_ebike_battery_level": "33%", "bike_id": "bike_209806", "name": "15516"}}, "434481": {"geometry": {"type": "Point", "coordinates": [-122.39311666666667, 47.53109333333333]}, "type": "Feature", "properties": {"time": 1564131817, "jump_ebike_battery_level": "35%", "bike_id": "bike_209806", "name": "15516"}}, "434480": {"geometry": {"type": "Point", "coordinates": [-122.39311666666667, 47.53109333333333]}, "type": "Feature", "properties": {"time": 1564128229, "jump_ebike_battery_level": "35%", "bike_id": "bike_209806", "name": "15516"}}, "434483": {"geometry": {"type": "Point", "coordinates": [-122.39311666666667, 47.53109333333333]}, "type": "Feature", "properties": {"time": 1564139030, "jump_ebike_battery_level": "36%", "bike_id": "bike_209806", "name": "15516"}}, "434482": {"geometry": {"type": "Point", "coordinates": [-122.39311666666667, 47.53109333333333]}, "type": "Feature", "properties": {"time": 1564135430, "jump_ebike_battery_level": "35%", "bike_id": "bike_209806", "name": "15516"}}, "434485": {"geometry": {"type": "Point", "coordinates": [-122.39311666666667, 47.53109333333333]}, "type": "Feature", "properties": {"time": 1564146217, "jump_ebike_battery_level": "36%", "bike_id": "bike_209806", "name": "15516"}}, "434484": {"geometry": {"type": "Point", "coordinates": [-122.39311666666667, 47.53109333333333]}, "type": "Feature", "properties": {"time": 1564142614, "jump_ebike_battery_level": "36%", "bike_id": "bike_209806", "name": "15516"}}, "434487": {"geometry": {"type": "Point", "coordinates": [-122.39311666666667, 47.53109333333333]}, "type": "Feature", "properties": {"time": 1564153429, "jump_ebike_battery_level": "33%", "bike_id": "bike_209806", "name": "15516"}}, "434486": {"geometry": {"type": "Point", "coordinates": [-122.39311666666667, 47.53109333333333]}, "type": "Feature", "properties": {"time": 1564149815, "jump_ebike_battery_level": "36%", "bike_id": "bike_209806", "name": "15516"}}, "434395": {"geometry": {"type": "Point", "coordinates": [-122.380795, 47.588995]}, "type": "Feature", "properties": {"time": 1563822218, "jump_ebike_battery_level": "44%", "bike_id": "bike_209806", "name": "15516"}}, "434394": {"geometry": {"type": "Point", "coordinates": [-122.380795, 47.588995]}, "type": "Feature", "properties": {"time": 1563818616, "jump_ebike_battery_level": "44%", "bike_id": "bike_209806", "name": "15516"}}, "434397": {"geometry": {"type": "Point", "coordinates": [-122.38124666666667, 47.589405]}, "type": "Feature", "properties": {"time": 1563829417, "jump_ebike_battery_level": "22%", "bike_id": "bike_209806", "name": "15516"}}, "434396": {"geometry": {"type": "Point", "coordinates": [-122.40648333333333, 47.58083666666667]}, "type": "Feature", "properties": {"time": 1563825829, "jump_ebike_battery_level": "26%", "bike_id": "bike_209806", "name": "15516"}}, "434391": {"geometry": {"type": "Point", "coordinates": [-122.37736666666666, 47.586664999999996]}, "type": "Feature", "properties": {"time": 1563807830, "jump_ebike_battery_level": "46%", "bike_id": "bike_209806", "name": "15516"}}, "434390": {"geometry": {"type": "Point", "coordinates": [-122.37736666666666, 47.586664999999996]}, "type": "Feature", "properties": {"time": 1563804217, "jump_ebike_battery_level": "48%", "bike_id": "bike_209806", "name": "15516"}}, "434393": {"geometry": {"type": "Point", "coordinates": [-122.380795, 47.588995]}, "type": "Feature", "properties": {"time": 1563815015, "jump_ebike_battery_level": "45%", "bike_id": "bike_209806", "name": "15516"}}, "434392": {"geometry": {"type": "Point", "coordinates": [-122.380795, 47.588995]}, "type": "Feature", "properties": {"time": 1563811413, "jump_ebike_battery_level": "45%", "bike_id": "bike_209806", "name": "15516"}}, "434399": {"geometry": {"type": "Point", "coordinates": [-122.40202666666667, 47.582838333333335]}, "type": "Feature", "properties": {"time": 1563836630, "jump_ebike_battery_level": "30%", "bike_id": "bike_209806", "name": "15516"}}, "434398": {"geometry": {"type": "Point", "coordinates": [-122.38124666666667, 47.589405]}, "type": "Feature", "properties": {"time": 1563833029, "jump_ebike_battery_level": "37%", "bike_id": "bike_209806", "name": "15516"}}, "434364": {"geometry": {"type": "Point", "coordinates": [-122.411455, 47.578975]}, "type": "Feature", "properties": {"time": 1563710413, "jump_ebike_battery_level": "89%", "bike_id": "bike_209806", "name": "15516"}}, "434365": {"geometry": {"type": "Point", "coordinates": [-122.411455, 47.578975]}, "type": "Feature", "properties": {"time": 1563714014, "jump_ebike_battery_level": "89%", "bike_id": "bike_209806", "name": "15516"}}, "434472": {"geometry": {"type": "Point", "coordinates": [-122.39311666666667, 47.53109333333333]}, "type": "Feature", "properties": {"time": 1564099418, "jump_ebike_battery_level": "40%", "bike_id": "bike_209806", "name": "15516"}}, "434367": {"geometry": {"type": "Point", "coordinates": [-122.411455, 47.578975]}, "type": "Feature", "properties": {"time": 1563724773, "jump_ebike_battery_level": "89%", "bike_id": "bike_209806", "name": "15516"}}, "434475": {"geometry": {"type": "Point", "coordinates": [-122.39311666666667, 47.53109333333333]}, "type": "Feature", "properties": {"time": 1564110229, "jump_ebike_battery_level": "39%", "bike_id": "bike_209806", "name": "15516"}}, "434476": {"geometry": {"type": "Point", "coordinates": [-122.39311666666667, 47.53109333333333]}, "type": "Feature", "properties": {"time": 1564113813, "jump_ebike_battery_level": "38%", "bike_id": "bike_209806", "name": "15516"}}, "434401": {"geometry": {"type": "Point", "coordinates": [-122.38022166666667, 47.588741666666664]}, "type": "Feature", "properties": {"time": 1563843829, "jump_ebike_battery_level": "24%", "bike_id": "bike_209806", "name": "15516"}}, "434403": {"geometry": {"type": "Point", "coordinates": [-122.41209166666667, 47.57877666666667]}, "type": "Feature", "properties": {"time": 1563851029, "jump_ebike_battery_level": "18%", "bike_id": "bike_209806", "name": "15516"}}, "434438": {"geometry": {"type": "Point", "coordinates": [-122.38199666666667, 47.590575]}, "type": "Feature", "properties": {"time": 1563977013, "jump_ebike_battery_level": "73%", "bike_id": "bike_209806", "name": "15516"}}, "434439": {"geometry": {"type": "Point", "coordinates": [-122.38199666666667, 47.590575]}, "type": "Feature", "properties": {"time": 1563980631, "jump_ebike_battery_level": "73%", "bike_id": "bike_209806", "name": "15516"}}, "434434": {"geometry": {"type": "Point", "coordinates": [-122.38195833333333, 47.590603333333334]}, "type": "Feature", "properties": {"time": 1563962615, "jump_ebike_battery_level": "73%", "bike_id": "bike_209806", "name": "15516"}}, "434435": {"geometry": {"type": "Point", "coordinates": [-122.38195833333333, 47.590603333333334]}, "type": "Feature", "properties": {"time": 1563966230, "jump_ebike_battery_level": "73%", "bike_id": "bike_209806", "name": "15516"}}, "434436": {"geometry": {"type": "Point", "coordinates": [-122.38195833333333, 47.590603333333334]}, "type": "Feature", "properties": {"time": 1563969814, "jump_ebike_battery_level": "73%", "bike_id": "bike_209806", "name": "15516"}}, "434437": {"geometry": {"type": "Point", "coordinates": [-122.38199666666667, 47.590575]}, "type": "Feature", "properties": {"time": 1563973430, "jump_ebike_battery_level": "73%", "bike_id": "bike_209806", "name": "15516"}}, "434430": {"geometry": {"type": "Point", "coordinates": [-122.38195833333333, 47.590603333333334]}, "type": "Feature", "properties": {"time": 1563948229, "jump_ebike_battery_level": "74%", "bike_id": "bike_209806", "name": "15516"}}, "434431": {"geometry": {"type": "Point", "coordinates": [-122.38195833333333, 47.590603333333334]}, "type": "Feature", "properties": {"time": 1563951817, "jump_ebike_battery_level": "75%", "bike_id": "bike_209806", "name": "15516"}}, "434432": {"geometry": {"type": "Point", "coordinates": [-122.38195833333333, 47.590603333333334]}, "type": "Feature", "properties": {"time": 1563955414, "jump_ebike_battery_level": "73%", "bike_id": "bike_209806", "name": "15516"}}, "434433": {"geometry": {"type": "Point", "coordinates": [-122.38195833333333, 47.590603333333334]}, "type": "Feature", "properties": {"time": 1563959018, "jump_ebike_battery_level": "73%", "bike_id": "bike_209806", "name": "15516"}}, "434458": {"geometry": {"type": "Point", "coordinates": [-122.393165, 47.52317166666667]}, "type": "Feature", "properties": {"time": 1564049029, "jump_ebike_battery_level": "56%", "bike_id": "bike_209806", "name": "15516"}}, "434459": {"geometry": {"type": "Point", "coordinates": [-122.393165, 47.52317166666667]}, "type": "Feature", "properties": {"time": 1564052614, "jump_ebike_battery_level": "56%", "bike_id": "bike_209806", "name": "15516"}}, "434456": {"geometry": {"type": "Point", "coordinates": [-122.393165, 47.52317166666667]}, "type": "Feature", "properties": {"time": 1564041830, "jump_ebike_battery_level": "56%", "bike_id": "bike_209806", "name": "15516"}}, "434457": {"geometry": {"type": "Point", "coordinates": [-122.393165, 47.52317166666667]}, "type": "Feature", "properties": {"time": 1564045429, "jump_ebike_battery_level": "56%", "bike_id": "bike_209806", "name": "15516"}}, "434454": {"geometry": {"type": "Point", "coordinates": [-122.393165, 47.52317166666667]}, "type": "Feature", "properties": {"time": 1564034613, "jump_ebike_battery_level": "57%", "bike_id": "bike_209806", "name": "15516"}}, "434455": {"geometry": {"type": "Point", "coordinates": [-122.393165, 47.52317166666667]}, "type": "Feature", "properties": {"time": 1564038213, "jump_ebike_battery_level": "57%", "bike_id": "bike_209806", "name": "15516"}}, "434452": {"geometry": {"type": "Point", "coordinates": [-122.393165, 47.52317166666667]}, "type": "Feature", "properties": {"time": 1564027430, "jump_ebike_battery_level": "59%", "bike_id": "bike_209806", "name": "15516"}}, "434453": {"geometry": {"type": "Point", "coordinates": [-122.393165, 47.52317166666667]}, "type": "Feature", "properties": {"time": 1564031029, "jump_ebike_battery_level": "59%", "bike_id": "bike_209806", "name": "15516"}}, "434450": {"geometry": {"type": "Point", "coordinates": [-122.393165, 47.52317166666667]}, "type": "Feature", "properties": {"time": 1564020219, "jump_ebike_battery_level": "59%", "bike_id": "bike_209806", "name": "15516"}}, "434451": {"geometry": {"type": "Point", "coordinates": [-122.393165, 47.52317166666667]}, "type": "Feature", "properties": {"time": 1564023830, "jump_ebike_battery_level": "59%", "bike_id": "bike_209806", "name": "15516"}}, "434429": {"geometry": {"type": "Point", "coordinates": [-122.38195833333333, 47.590603333333334]}, "type": "Feature", "properties": {"time": 1563944614, "jump_ebike_battery_level": "76%", "bike_id": "bike_209806", "name": "15516"}}, "434428": {"geometry": {"type": "Point", "coordinates": [-122.38195833333333, 47.590603333333334]}, "type": "Feature", "properties": {"time": 1563941029, "jump_ebike_battery_level": "76%", "bike_id": "bike_209806", "name": "15516"}}, "434422": {"geometry": {"type": "Point", "coordinates": [-122.40973166666667, 47.57949]}, "type": "Feature", "properties": {"time": 1563919430, "jump_ebike_battery_level": "81%", "bike_id": "bike_209806", "name": "15516"}}, "434421": {"geometry": {"type": "Point", "coordinates": [-122.40973166666667, 47.57949]}, "type": "Feature", "properties": {"time": 1563915818, "jump_ebike_battery_level": "81%", "bike_id": "bike_209806", "name": "15516"}}, "434427": {"geometry": {"type": "Point", "coordinates": [-122.38195833333333, 47.590603333333334]}, "type": "Feature", "properties": {"time": 1563937430, "jump_ebike_battery_level": "76%", "bike_id": "bike_209806", "name": "15516"}}, "434426": {"geometry": {"type": "Point", "coordinates": [-122.38195833333333, 47.590603333333334]}, "type": "Feature", "properties": {"time": 1563933829, "jump_ebike_battery_level": "77%", "bike_id": "bike_209806", "name": "15516"}}, "434449": {"geometry": {"type": "Point", "coordinates": [-122.393165, 47.52317166666667]}, "type": "Feature", "properties": {"time": 1564016630, "jump_ebike_battery_level": "55%", "bike_id": "bike_209806", "name": "15516"}}, "434448": {"geometry": {"type": "Point", "coordinates": [-122.38194666666666, 47.590588333333336]}, "type": "Feature", "properties": {"time": 1564013017, "jump_ebike_battery_level": "69%", "bike_id": "bike_209806", "name": "15516"}}, "434445": {"geometry": {"type": "Point", "coordinates": [-122.38194666666666, 47.590588333333336]}, "type": "Feature", "properties": {"time": 1564002230, "jump_ebike_battery_level": "70%", "bike_id": "bike_209806", "name": "15516"}}, "434444": {"geometry": {"type": "Point", "coordinates": [-122.38194666666666, 47.590588333333336]}, "type": "Feature", "properties": {"time": 1563998615, "jump_ebike_battery_level": "71%", "bike_id": "bike_209806", "name": "15516"}}, "434447": {"geometry": {"type": "Point", "coordinates": [-122.38194666666666, 47.590588333333336]}, "type": "Feature", "properties": {"time": 1564009429, "jump_ebike_battery_level": "69%", "bike_id": "bike_209806", "name": "15516"}}, "434446": {"geometry": {"type": "Point", "coordinates": [-122.38194666666666, 47.590588333333336]}, "type": "Feature", "properties": {"time": 1564005829, "jump_ebike_battery_level": "70%", "bike_id": "bike_209806", "name": "15516"}}, "434441": {"geometry": {"type": "Point", "coordinates": [-122.38194666666666, 47.590588333333336]}, "type": "Feature", "properties": {"time": 1563987830, "jump_ebike_battery_level": "71%", "bike_id": "bike_209806", "name": "15516"}}, "434440": {"geometry": {"type": "Point", "coordinates": [-122.38199666666667, 47.590575]}, "type": "Feature", "properties": {"time": 1563984230, "jump_ebike_battery_level": "72%", "bike_id": "bike_209806", "name": "15516"}}, "434443": {"geometry": {"type": "Point", "coordinates": [-122.38194666666666, 47.590588333333336]}, "type": "Feature", "properties": {"time": 1563995030, "jump_ebike_battery_level": "71%", "bike_id": "bike_209806", "name": "15516"}}, "434442": {"geometry": {"type": "Point", "coordinates": [-122.38194666666666, 47.590588333333336]}, "type": "Feature", "properties": {"time": 1563991418, "jump_ebike_battery_level": "71%", "bike_id": "bike_209806", "name": "15516"}}, "434478": {"geometry": {"type": "Point", "coordinates": [-122.39311666666667, 47.53109333333333]}, "type": "Feature", "properties": {"time": 1564121029, "jump_ebike_battery_level": "37%", "bike_id": "bike_209806", "name": "15516"}}, "434479": {"geometry": {"type": "Point", "coordinates": [-122.39311666666667, 47.53109333333333]}, "type": "Feature", "properties": {"time": 1564124618, "jump_ebike_battery_level": "37%", "bike_id": "bike_209806", "name": "15516"}}, "434369": {"geometry": {"type": "Point", "coordinates": [-122.40494166666667, 47.581495]}, "type": "Feature", "properties": {"time": 1563731974, "jump_ebike_battery_level": "72%", "bike_id": "bike_209806", "name": "15516"}}, "434470": {"geometry": {"type": "Point", "coordinates": [-122.39047, 47.52064]}, "type": "Feature", "properties": {"time": 1564092283, "jump_ebike_battery_level": "47%", "bike_id": "bike_209806", "name": "15516"}}, "434471": {"geometry": {"type": "Point", "coordinates": [-122.39311666666667, 47.53109333333333]}, "type": "Feature", "properties": {"time": 1564095829, "jump_ebike_battery_level": "41%", "bike_id": "bike_209806", "name": "15516"}}, "434366": {"geometry": {"type": "Point", "coordinates": [-122.411455, 47.578975]}, "type": "Feature", "properties": {"time": 1563717614, "jump_ebike_battery_level": "89%", "bike_id": "bike_209806", "name": "15516"}}, "434473": {"geometry": {"type": "Point", "coordinates": [-122.39311666666667, 47.53109333333333]}, "type": "Feature", "properties": {"time": 1564103030, "jump_ebike_battery_level": "40%", "bike_id": "bike_209806", "name": "15516"}}, "434474": {"geometry": {"type": "Point", "coordinates": [-122.39311666666667, 47.53109333333333]}, "type": "Feature", "properties": {"time": 1564106617, "jump_ebike_battery_level": "39%", "bike_id": "bike_209806", "name": "15516"}}, "434361": {"geometry": {"type": "Point", "coordinates": [-122.411455, 47.578975]}, "type": "Feature", "properties": {"time": 1563699613, "jump_ebike_battery_level": "83%", "bike_id": "bike_209806", "name": "15516"}}, "434362": {"geometry": {"type": "Point", "coordinates": [-122.411455, 47.578975]}, "type": "Feature", "properties": {"time": 1563706777, "jump_ebike_battery_level": "90%", "bike_id": "bike_209806", "name": "15516"}}, "434477": {"geometry": {"type": "Point", "coordinates": [-122.39311666666667, 47.53109333333333]}, "type": "Feature", "properties": {"time": 1564117412, "jump_ebike_battery_level": "38%", "bike_id": "bike_209806", "name": "15516"}}}