{"434370": {"geometry": {"type": "Point", "coordinates": [-122.35444, 47.65392]}, "type": "Feature", "properties": {"time": 1563735574, "jump_ebike_battery_level": "24%", "bike_id": "bike_91250", "name": "28768"}}, "434369": {"geometry": {"type": "Point", "coordinates": [-122.35444, 47.65392]}, "type": "Feature", "properties": {"time": 1563731974, "jump_ebike_battery_level": "25%", "bike_id": "bike_91250", "name": "28768"}}, "434364": {"geometry": {"type": "Point", "coordinates": [-122.36324333333333, 47.675911666666664]}, "type": "Feature", "properties": {"time": 1563710413, "jump_ebike_battery_level": "30%", "bike_id": "bike_91250", "name": "28768"}}, "434365": {"geometry": {"type": "Point", "coordinates": [-122.36324333333333, 47.675911666666664]}, "type": "Feature", "properties": {"time": 1563714014, "jump_ebike_battery_level": "30%", "bike_id": "bike_91250", "name": "28768"}}, "434366": {"geometry": {"type": "Point", "coordinates": [-122.36324333333333, 47.675911666666664]}, "type": "Feature", "properties": {"time": 1563717614, "jump_ebike_battery_level": "30%", "bike_id": "bike_91250", "name": "28768"}}, "434367": {"geometry": {"type": "Point", "coordinates": [-122.36324333333333, 47.675911666666664]}, "type": "Feature", "properties": {"time": 1563724773, "jump_ebike_battery_level": "29%", "bike_id": "bike_91250", "name": "28768"}}, "434376": {"geometry": {"type": "Point", "coordinates": [-122.35444, 47.65392]}, "type": "Feature", "properties": {"time": 1563753613, "jump_ebike_battery_level": "22%", "bike_id": "bike_91250", "name": "28768"}}, "434361": {"geometry": {"type": "Point", "coordinates": [-122.36324333333333, 47.675911666666664]}, "type": "Feature", "properties": {"time": 1563699613, "jump_ebike_battery_level": "31%", "bike_id": "bike_91250", "name": "28768"}}, "434362": {"geometry": {"type": "Point", "coordinates": [-122.36324333333333, 47.675911666666664]}, "type": "Feature", "properties": {"time": 1563706777, "jump_ebike_battery_level": "30%", "bike_id": "bike_91250", "name": "28768"}}, "434374": {"geometry": {"type": "Point", "coordinates": [-122.35444, 47.65392]}, "type": "Feature", "properties": {"time": 1563749972, "jump_ebike_battery_level": "22%", "bike_id": "bike_91250", "name": "28768"}}, "434423": {"geometry": {"type": "Point", "coordinates": [-122.33646333333333, 47.64533333333333]}, "type": "Feature", "properties": {"time": 1563923019, "jump_ebike_battery_level": "84%", "bike_id": "bike_91250", "name": "28768"}}, "434378": {"geometry": {"type": "Point", "coordinates": [-122.35444, 47.65392]}, "type": "Feature", "properties": {"time": 1563764375, "jump_ebike_battery_level": "21%", "bike_id": "bike_91250", "name": "28768"}}, "434372": {"geometry": {"type": "Point", "coordinates": [-122.35444, 47.65392]}, "type": "Feature", "properties": {"time": 1563742771, "jump_ebike_battery_level": "23%", "bike_id": "bike_91250", "name": "28768"}}, "434377": {"geometry": {"type": "Point", "coordinates": [-122.35444, 47.65392]}, "type": "Feature", "properties": {"time": 1563757213, "jump_ebike_battery_level": "22%", "bike_id": "bike_91250", "name": "28768"}}, "434422": {"geometry": {"type": "Point", "coordinates": [-122.33646333333333, 47.64533333333333]}, "type": "Feature", "properties": {"time": 1563919430, "jump_ebike_battery_level": "84%", "bike_id": "bike_91250", "name": "28768"}}, "434371": {"geometry": {"type": "Point", "coordinates": [-122.35444, 47.65392]}, "type": "Feature", "properties": {"time": 1563739174, "jump_ebike_battery_level": "24%", "bike_id": "bike_91250", "name": "28768"}}, "434425": {"geometry": {"type": "Point", "coordinates": [-122.33646333333333, 47.64533333333333]}, "type": "Feature", "properties": {"time": 1563930229, "jump_ebike_battery_level": "83%", "bike_id": "bike_91250", "name": "28768"}}, "434424": {"geometry": {"type": "Point", "coordinates": [-122.33646333333333, 47.64533333333333]}, "type": "Feature", "properties": {"time": 1563926619, "jump_ebike_battery_level": "84%", "bike_id": "bike_91250", "name": "28768"}}}