{"434438": {"geometry": {"type": "Point", "coordinates": [-122.34381833333333, 47.611983333333335]}, "type": "Feature", "properties": {"time": 1563977013, "jump_ebike_battery_level": "86%", "bike_id": "bike_211994", "name": "55000"}}, "434439": {"geometry": {"type": "Point", "coordinates": [-122.34381833333333, 47.611983333333335]}, "type": "Feature", "properties": {"time": 1563980631, "jump_ebike_battery_level": "86%", "bike_id": "bike_211994", "name": "55000"}}, "434436": {"geometry": {"type": "Point", "coordinates": [-122.34381833333333, 47.611983333333335]}, "type": "Feature", "properties": {"time": 1563969814, "jump_ebike_battery_level": "86%", "bike_id": "bike_211994", "name": "55000"}}, "434437": {"geometry": {"type": "Point", "coordinates": [-122.34381833333333, 47.611983333333335]}, "type": "Feature", "properties": {"time": 1563973430, "jump_ebike_battery_level": "86%", "bike_id": "bike_211994", "name": "55000"}}, "434458": {"geometry": {"type": "Point", "coordinates": [-122.335255, 47.648601666666664]}, "type": "Feature", "properties": {"time": 1564049029, "jump_ebike_battery_level": "59%", "bike_id": "bike_211994", "name": "55000"}}, "434459": {"geometry": {"type": "Point", "coordinates": [-122.335255, 47.648601666666664]}, "type": "Feature", "properties": {"time": 1564052614, "jump_ebike_battery_level": "59%", "bike_id": "bike_211994", "name": "55000"}}, "434456": {"geometry": {"type": "Point", "coordinates": [-122.335255, 47.648601666666664]}, "type": "Feature", "properties": {"time": 1564041830, "jump_ebike_battery_level": "59%", "bike_id": "bike_211994", "name": "55000"}}, "434457": {"geometry": {"type": "Point", "coordinates": [-122.335255, 47.648601666666664]}, "type": "Feature", "properties": {"time": 1564045429, "jump_ebike_battery_level": "59%", "bike_id": "bike_211994", "name": "55000"}}, "434454": {"geometry": {"type": "Point", "coordinates": [-122.335255, 47.648601666666664]}, "type": "Feature", "properties": {"time": 1564034613, "jump_ebike_battery_level": "61%", "bike_id": "bike_211994", "name": "55000"}}, "434455": {"geometry": {"type": "Point", "coordinates": [-122.335255, 47.648601666666664]}, "type": "Feature", "properties": {"time": 1564038213, "jump_ebike_battery_level": "61%", "bike_id": "bike_211994", "name": "55000"}}, "434452": {"geometry": {"type": "Point", "coordinates": [-122.335255, 47.648601666666664]}, "type": "Feature", "properties": {"time": 1564027430, "jump_ebike_battery_level": "62%", "bike_id": "bike_211994", "name": "55000"}}, "434453": {"geometry": {"type": "Point", "coordinates": [-122.335255, 47.648601666666664]}, "type": "Feature", "properties": {"time": 1564031029, "jump_ebike_battery_level": "61%", "bike_id": "bike_211994", "name": "55000"}}, "434450": {"geometry": {"type": "Point", "coordinates": [-122.335255, 47.648601666666664]}, "type": "Feature", "properties": {"time": 1564020219, "jump_ebike_battery_level": "62%", "bike_id": "bike_211994", "name": "55000"}}, "434451": {"geometry": {"type": "Point", "coordinates": [-122.335255, 47.648601666666664]}, "type": "Feature", "properties": {"time": 1564023830, "jump_ebike_battery_level": "62%", "bike_id": "bike_211994", "name": "55000"}}, "434490": {"geometry": {"type": "Point", "coordinates": [-122.33628666666667, 47.66419]}, "type": "Feature", "properties": {"time": 1564164217, "jump_ebike_battery_level": "89%", "bike_id": "bike_211994", "name": "55000"}}, "434467": {"geometry": {"type": "Point", "coordinates": [-122.335255, 47.648601666666664]}, "type": "Feature", "properties": {"time": 1564081430, "jump_ebike_battery_level": "56%", "bike_id": "bike_211994", "name": "55000"}}, "434466": {"geometry": {"type": "Point", "coordinates": [-122.335255, 47.648601666666664]}, "type": "Feature", "properties": {"time": 1564077815, "jump_ebike_battery_level": "56%", "bike_id": "bike_211994", "name": "55000"}}, "434465": {"geometry": {"type": "Point", "coordinates": [-122.335255, 47.648601666666664]}, "type": "Feature", "properties": {"time": 1564074216, "jump_ebike_battery_level": "57%", "bike_id": "bike_211994", "name": "55000"}}, "434464": {"geometry": {"type": "Point", "coordinates": [-122.335255, 47.648601666666664]}, "type": "Feature", "properties": {"time": 1564070629, "jump_ebike_battery_level": "57%", "bike_id": "bike_211994", "name": "55000"}}, "434463": {"geometry": {"type": "Point", "coordinates": [-122.335255, 47.648601666666664]}, "type": "Feature", "properties": {"time": 1564067030, "jump_ebike_battery_level": "58%", "bike_id": "bike_211994", "name": "55000"}}, "434462": {"geometry": {"type": "Point", "coordinates": [-122.335255, 47.648601666666664]}, "type": "Feature", "properties": {"time": 1564063418, "jump_ebike_battery_level": "59%", "bike_id": "bike_211994", "name": "55000"}}, "434461": {"geometry": {"type": "Point", "coordinates": [-122.335255, 47.648601666666664]}, "type": "Feature", "properties": {"time": 1564059830, "jump_ebike_battery_level": "59%", "bike_id": "bike_211994", "name": "55000"}}, "434460": {"geometry": {"type": "Point", "coordinates": [-122.335255, 47.648601666666664]}, "type": "Feature", "properties": {"time": 1564056230, "jump_ebike_battery_level": "59%", "bike_id": "bike_211994", "name": "55000"}}, "434469": {"geometry": {"type": "Point", "coordinates": [-122.335255, 47.648601666666664]}, "type": "Feature", "properties": {"time": 1564088629, "jump_ebike_battery_level": "55%", "bike_id": "bike_211994", "name": "55000"}}, "434468": {"geometry": {"type": "Point", "coordinates": [-122.335255, 47.648601666666664]}, "type": "Feature", "properties": {"time": 1564085016, "jump_ebike_battery_level": "55%", "bike_id": "bike_211994", "name": "55000"}}, "434449": {"geometry": {"type": "Point", "coordinates": [-122.335255, 47.648601666666664]}, "type": "Feature", "properties": {"time": 1564016630, "jump_ebike_battery_level": "63%", "bike_id": "bike_211994", "name": "55000"}}, "434448": {"geometry": {"type": "Point", "coordinates": [-122.335255, 47.648601666666664]}, "type": "Feature", "properties": {"time": 1564013017, "jump_ebike_battery_level": "64%", "bike_id": "bike_211994", "name": "55000"}}, "434445": {"geometry": {"type": "Point", "coordinates": [-122.341225, 47.627071666666666]}, "type": "Feature", "properties": {"time": 1564002230, "jump_ebike_battery_level": "69%", "bike_id": "bike_211994", "name": "55000"}}, "434444": {"geometry": {"type": "Point", "coordinates": [-122.33646333333333, 47.61165833333333]}, "type": "Feature", "properties": {"time": 1563998615, "jump_ebike_battery_level": "73%", "bike_id": "bike_211994", "name": "55000"}}, "434447": {"geometry": {"type": "Point", "coordinates": [-122.335255, 47.648601666666664]}, "type": "Feature", "properties": {"time": 1564009429, "jump_ebike_battery_level": "63%", "bike_id": "bike_211994", "name": "55000"}}, "434446": {"geometry": {"type": "Point", "coordinates": [-122.335255, 47.648601666666664]}, "type": "Feature", "properties": {"time": 1564005829, "jump_ebike_battery_level": "63%", "bike_id": "bike_211994", "name": "55000"}}, "434441": {"geometry": {"type": "Point", "coordinates": [-122.31659833333333, 47.61274]}, "type": "Feature", "properties": {"time": 1563987830, "jump_ebike_battery_level": "72%", "bike_id": "bike_211994", "name": "55000"}}, "434440": {"geometry": {"type": "Point", "coordinates": [-122.34381833333333, 47.611983333333335]}, "type": "Feature", "properties": {"time": 1563984230, "jump_ebike_battery_level": "89%", "bike_id": "bike_211994", "name": "55000"}}, "434443": {"geometry": {"type": "Point", "coordinates": [-122.33646333333333, 47.61165833333333]}, "type": "Feature", "properties": {"time": 1563995030, "jump_ebike_battery_level": "73%", "bike_id": "bike_211994", "name": "55000"}}, "434442": {"geometry": {"type": "Point", "coordinates": [-122.33646333333333, 47.61165833333333]}, "type": "Feature", "properties": {"time": 1563991418, "jump_ebike_battery_level": "73%", "bike_id": "bike_211994", "name": "55000"}}, "434489": {"geometry": {"type": "Point", "coordinates": [-122.33628666666667, 47.66419]}, "type": "Feature", "properties": {"time": 1564160617, "jump_ebike_battery_level": "89%", "bike_id": "bike_211994", "name": "55000"}}, "434488": {"geometry": {"type": "Point", "coordinates": [-122.33628666666667, 47.66419]}, "type": "Feature", "properties": {"time": 1564157029, "jump_ebike_battery_level": "89%", "bike_id": "bike_211994", "name": "55000"}}, "434481": {"geometry": {"type": "Point", "coordinates": [-122.33634666666667, 47.66420166666666]}, "type": "Feature", "properties": {"time": 1564131817, "jump_ebike_battery_level": "43%", "bike_id": "bike_211994", "name": "55000"}}, "434480": {"geometry": {"type": "Point", "coordinates": [-122.335255, 47.648601666666664]}, "type": "Feature", "properties": {"time": 1564128229, "jump_ebike_battery_level": "48%", "bike_id": "bike_211994", "name": "55000"}}, "434483": {"geometry": {"type": "Point", "coordinates": [-122.33634666666667, 47.66420166666666]}, "type": "Feature", "properties": {"time": 1564139030, "jump_ebike_battery_level": "43%", "bike_id": "bike_211994", "name": "55000"}}, "434482": {"geometry": {"type": "Point", "coordinates": [-122.33634666666667, 47.66420166666666]}, "type": "Feature", "properties": {"time": 1564135430, "jump_ebike_battery_level": "43%", "bike_id": "bike_211994", "name": "55000"}}, "434485": {"geometry": {"type": "Point", "coordinates": [-122.33628666666667, 47.66419]}, "type": "Feature", "properties": {"time": 1564146217, "jump_ebike_battery_level": "84%", "bike_id": "bike_211994", "name": "55000"}}, "434484": {"geometry": {"type": "Point", "coordinates": [-122.33628666666667, 47.66419]}, "type": "Feature", "properties": {"time": 1564142614, "jump_ebike_battery_level": "84%", "bike_id": "bike_211994", "name": "55000"}}, "434487": {"geometry": {"type": "Point", "coordinates": [-122.33628666666667, 47.66419]}, "type": "Feature", "properties": {"time": 1564153429, "jump_ebike_battery_level": "90%", "bike_id": "bike_211994", "name": "55000"}}, "434486": {"geometry": {"type": "Point", "coordinates": [-122.33628666666667, 47.66419]}, "type": "Feature", "properties": {"time": 1564149815, "jump_ebike_battery_level": "84%", "bike_id": "bike_211994", "name": "55000"}}, "434478": {"geometry": {"type": "Point", "coordinates": [-122.335255, 47.648601666666664]}, "type": "Feature", "properties": {"time": 1564121029, "jump_ebike_battery_level": "49%", "bike_id": "bike_211994", "name": "55000"}}, "434479": {"geometry": {"type": "Point", "coordinates": [-122.335255, 47.648601666666664]}, "type": "Feature", "properties": {"time": 1564124618, "jump_ebike_battery_level": "49%", "bike_id": "bike_211994", "name": "55000"}}, "434470": {"geometry": {"type": "Point", "coordinates": [-122.335255, 47.648601666666664]}, "type": "Feature", "properties": {"time": 1564092283, "jump_ebike_battery_level": "54%", "bike_id": "bike_211994", "name": "55000"}}, "434471": {"geometry": {"type": "Point", "coordinates": [-122.335255, 47.648601666666664]}, "type": "Feature", "properties": {"time": 1564095829, "jump_ebike_battery_level": "54%", "bike_id": "bike_211994", "name": "55000"}}, "434472": {"geometry": {"type": "Point", "coordinates": [-122.335255, 47.648601666666664]}, "type": "Feature", "properties": {"time": 1564099418, "jump_ebike_battery_level": "53%", "bike_id": "bike_211994", "name": "55000"}}, "434473": {"geometry": {"type": "Point", "coordinates": [-122.335255, 47.648601666666664]}, "type": "Feature", "properties": {"time": 1564103030, "jump_ebike_battery_level": "52%", "bike_id": "bike_211994", "name": "55000"}}, "434474": {"geometry": {"type": "Point", "coordinates": [-122.335255, 47.648601666666664]}, "type": "Feature", "properties": {"time": 1564106617, "jump_ebike_battery_level": "52%", "bike_id": "bike_211994", "name": "55000"}}, "434475": {"geometry": {"type": "Point", "coordinates": [-122.335255, 47.648601666666664]}, "type": "Feature", "properties": {"time": 1564110229, "jump_ebike_battery_level": "51%", "bike_id": "bike_211994", "name": "55000"}}, "434476": {"geometry": {"type": "Point", "coordinates": [-122.335255, 47.648601666666664]}, "type": "Feature", "properties": {"time": 1564113813, "jump_ebike_battery_level": "50%", "bike_id": "bike_211994", "name": "55000"}}, "434477": {"geometry": {"type": "Point", "coordinates": [-122.335255, 47.648601666666664]}, "type": "Feature", "properties": {"time": 1564117412, "jump_ebike_battery_level": "50%", "bike_id": "bike_211994", "name": "55000"}}, "434403": {"geometry": {"type": "Point", "coordinates": [-122.34269333333333, 47.622185]}, "type": "Feature", "properties": {"time": 1563851029, "jump_ebike_battery_level": "90%", "bike_id": "bike_211994", "name": "55000"}}, "434404": {"geometry": {"type": "Point", "coordinates": [-122.34269333333333, 47.622185]}, "type": "Feature", "properties": {"time": 1563854615, "jump_ebike_battery_level": "90%", "bike_id": "bike_211994", "name": "55000"}}}